pasteboard/__init__.py
pasteboard/__init__.pyi
pasteboard/_native.cpython-39-darwin.so
pasteboard/pasteboard.m
pasteboard/py.typed
pasteboard-0.4.0.dist-info/LICENSE
pasteboard-0.4.0.dist-info/METADATA
pasteboard-0.4.0.dist-info/WHEEL
pasteboard-0.4.0.dist-info/top_level.txt
pasteboard-0.4.0.dist-info/RECORD
