Metadata-Version: 2.1
Name: pasteboard
Version: 0.4.0
Summary: Pasteboard - Python interface for reading from NSPasteboard (macOS clipboard)
Author-email: Toby Fleming <tobywf@users.noreply.github.com>
License: Mozilla Public License Version 2.0
Keywords: macOS,clipboard,pasteboard
Classifier: Development Status :: 4 - Beta
Classifier: Environment :: MacOS X :: Cocoa
Classifier: Intended Audience :: Developers
Classifier: Natural Language :: English
Classifier: Operating System :: MacOS :: MacOS X
Classifier: License :: OSI Approved :: Mozilla Public License 2.0 (MPL 2.0)
Classifier: Programming Language :: Objective C
Classifier: Programming Language :: Python :: 3 :: Only
Classifier: Programming Language :: Python :: 3.8
Classifier: Programming Language :: Python :: 3.9
Classifier: Programming Language :: Python :: 3.10
Classifier: Programming Language :: Python :: 3.11
Classifier: Programming Language :: Python :: 3.12
Classifier: Programming Language :: Python :: Implementation :: CPython
Classifier: Topic :: Desktop Environment
Classifier: Topic :: Software Development :: Libraries
Requires-Python: >=3.8
License-File: LICENSE
Provides-Extra: dev
Requires-Dist: pytest ==7.4.4 ; extra == 'dev'
Requires-Dist: hypothesis ==6.93.0 ; extra == 'dev'
Requires-Dist: black ==23.12.1 ; extra == 'dev'
Requires-Dist: mypy ==1.8.0 ; extra == 'dev'
Requires-Dist: pre-commit ==3.5.0 ; extra == 'dev'
